<text xmlns="http://www.tei-c.org/ns/1.0" xml:id="originaltext"><body><div><pb n="15r" facs="#fol15r"/>
         <p>la terra quale he asai piu potente de legente fo
            <lb/>restiere prendera partito.  Aricordo reverete
            <lb/>mente ala prelibata S. v. lecose como lepassa
            <lb/>no proveda quela per sua suma sapientia co
            <lb/>mo gli pare et piace. agli piedi de la quale p<ex>ro</ex>
            <lb/>strato humelemente sempre ala gratia sua
            <lb/>me aricomando.
            <lb/>littere simultande ex serie suprascripta(rum)
            <lb/><expan>l<ex>iter</ex>ra<ex>rum</ex></expan> uno mo<ex>do</ex> et emand<ex>a</ex>e ut supra
            <lb/>PRobissime vir uno homo darme chiama
            <lb/>to zoane a zucarate de calabria ha per
            <lb/>prigioni pietro cione nostro et compagni altri
            <lb/>tanto gravi deche pregai bene perparte de epsi
            <lb/>pregioni vostro fratello serviesse ala probitate
            <lb/>v. q<ex>uan</ex>to me acadea rechiedervi de subventione de di
            <lb/>nari per riscoter quigli ad hora simelmente ad
            <lb/>quela significo como habiamo fato guarda<ex>r</ex>e
            <lb/>de le cose robe et dinari cebixogna et per la ta
            <lb/>glia vole epso zoane che he ducati.  lo adiman
            <lb/>da seraci fatica da tenire modo lo aspeti per uno
            <lb/>mexe stretamente El che fa mistiero la probita
            <lb/>ten proveda o disecorso de dinari velocissimo
            <lb/>per questa suma como continuamente ainost<ex>ri</ex>
            <lb/>bixogni haveti subvenuto et per mie altre gia lo<ex>n</ex>
         </p>
         </div></body></text>